[
    {
        "file": "RZO11.mp3",
        "answer": "Re:Zero 1сезон 1опенинг"
    },
    {
        "file": "91DO.mp3",
        "answer": "91 День"
    },
    {
        "file": "ADO.mp3",
        "answer": "Ангел кровопролития"
    },    {
        "file": "AKSO.mp3",
        "answer": "Некий научный акселератор"
    },
    {
        "file": "AO.mp3",
        "answer": "Иная"
    },
    {
        "file": "ATO2.mp3",
        "answer": "Атака титанов 2сезон"
    },
    {
        "file": "ATO11.mp3",
        "answer": "Атака титанов 1сезон 1опенинг"
    },
    {
        "file": "ATO12.mp3",
        "answer": "Атака титанов 1сезон 2опенинг"
    },
    {
        "file": "ATO31.mp3",
        "answer": "Атака титанов 3сезон 1опенинг"
    },
    {
        "file": "ATO32.mp3",
        "answer": "Атака титанов 3сезон 2опенинг"
    },
    {
        "file": "BCO1.mp3",
        "answer": "Чёрный клевер 1опенинг"
    },
    {
        "file": "BCO2.mp3",
        "answer": "Чёрный клевер 2опенинг"
    },
    {
        "file": "BCO3.mp3",
        "answer": "Чёрный клевер 3опенинг"
    },
    {
        "file": "BDGIMO.mp3",
        "answer": "Город, в котором меня нет"
    },
    {
        "file": "BO1.mp3",
        "answer": "Берсерк 1сезон"
    },
    {
        "file": "CGO1.mp3",
        "answer": "Код Гиас 1опенинг"
    },
    {
        "file": "CGO4.mp3",
        "answer": "Код Гиас 4опенинг"
    },
    {
        "file": "CGO5.mp3",
        "answer": "Код Гиас 5опенинг"
    },
    {
        "file": "CLASSO1.mp3",
        "answer": "Класс превосходства 1сезон"
    },
    {
        "file": "DFO1.mp3",
        "answer": "Милый во Франксе 1сезон"
    },
    {
        "file": "DNO1.mp3",
        "answer": "Тетрадь смерти 1опенинг"
    },
    {
        "file": "DNO2.mp3",
        "answer": "Тетрадь смерти 2опенинг"
    },
    {
        "file": "DOO1.mp3",
        "answer": "Дороро 1опенинг"
    },
    {
        "file": "DOO2.mp3",
        "answer": "Дороро 2опенинг"
    },
    {
        "file": "DRSO11.mp3",
        "answer": "Доктор Стоун 1сезон 1опенинг"
    },
    {
        "file": "DRSO12.mp3",
        "answer": "Доктор Стоун 1сезон 2опенинг"
    },
    {
        "file": "DSO.mp3",
        "answer": "Клинок, рассекающий демонов 1сезон"
    },
    {
        "file": "ECO3.mp3",
        "answer": "Радость подъёма 3сезон"
    },
    {
        "file": "ECO21.mp3",
        "answer": "Радость подъёма 2сезон 1опенинг"
    },
    {
        "file": "FSSO.mp3",
        "answer": "Назойливая лисица Сенко-Сан"
    },
    {
        "file": "GBO.mp3",
        "answer": "Необъятный океан"
    },
    {
        "file": "GDOO.mp3",
        "answer": "Габриэль бросает школу"
    },
    {
        "file": "HELO.mp3",
        "answer": "Хеллсинг"
    },
    {
        "file": "RSHO21.mp3",
        "answer": "Восхождение героя щита 2сезон"
    },
    {
        "file": "HIRSO11.mp3",
        "answer": "О моём перерождении в слизь 1сезон 1опенинг"
    },
    {
        "file": "HIRSO12.mp3",
        "answer": "О моём перерождении в слизь 1сезон 2опенинг"
    },
    {
        "file": "HIRSO21.mp3",
        "answer": "О моём перерождении в слизь 2сезон 1опенинг"
    },
    {
        "file": "HIRSO22.mp3",
        "answer": "О моём перерождении в слизь 2сезон 2опенинг"
    },
    {
        "file": "HOO1.mp3",
        "answer": "Тяжёлый объект 1опенинг"
    },
    {
        "file": "HOO2.mp3",
        "answer": "Тяжёлый объект 2опенинг"
    },
    {
        "file": "IIWTTPFDO1.mp3",
        "answer": "В подземелье я пойду, там красавицу найду 1сезон"
    },
    {
        "file": "IIWTTPFDO2.mp3",
        "answer": "В подземелье я пойду, там красавицу найду 2сезон"
    },
    {
        "file": "IIWTTPFDO3.mp3",
        "answer": "В подземелье я пойду, там красавицу найду 3сезон"
    },
    {
        "file": "JOO3.mp3",
        "answer": "Невероятные приключения ДжоДжо 2сезон"
    },
    {
        "file": "JOO4.mp3",
        "answer": "Невероятные приключения ДжоДжо 3сезон"
    },
    {
        "file": "KONOSUBAO1.mp3",
        "answer": "Коносуба 1сезон"
    },
    {
        "file": "KONOSUBAO2.mp3",
        "answer": "Коносуба 2сезон"
    },
    {
        "file": "KSO.mp3",
        "answer": "Печать ветра"
    },
    {
        "file": "LCODO1.mp3",
        "answer": "Чудачества любви не помеха 1сезон"
    },
    {
        "file": "LCODO2.mp3",
        "answer": "Чудачества любви не помеха 2сезон"
    },
    {
        "file": "MNO1.mp3",
        "answer": "Дневник будущего 1опенинг"
    },
    {
        "file": "MNO2.mp3",
        "answer": "Дневник будущего 2опенинг"
    },
    {
        "file": "NO12.mp3",
        "answer": "Наруто 1сезон 2опенинг"
    },
    {
        "file": "NO21.mp3",
        "answer": "Наруто 2сезон 1опенинг"
    },
    {
        "file": "NO23.mp3",
        "answer": "Наруто 2сезон 3опенинг"
    },
    {
        "file": "NO24.mp3",
        "answer": "Наруто 2сезон 4опенинг"
    },
    {
        "file": "NO25.mp3",
        "answer": "Наруто 2сезон 5опенинг"
    },
    {
        "file": "NO26.mp3",
        "answer": "Наруто 2сезон 6опенинг"
    },
    {
        "file": "NAO2.mp3",
        "answer": "Бездомный Бог 2опенинг"
    },
    {
        "file": "PARO.mp3",
        "answer": "Паразит"
    },
    {
        "file": "PNO1.mp3",
        "answer": "Обещанный Неверленд"
    },
    {
        "file": "RSHO11.mp3",
        "answer": "Восхождение героя щита 1сезон 1опенинг"
    },
    {
        "file": "RSHO12.mp3",
        "answer": "Восхождение героя щита 1сезон 2опенинг"
    },
    {
        "file": "RZO12.mp3",
        "answer": "Re:Zero 1сезон 2опенинг"
    },
    {
        "file": "RZO21.mp3",
        "answer": "Re:Zero 2сезон 1опенинг"
    },
    {
        "file": "RZO22.mp3",
        "answer": "Re:Zero 2сезон 2опенинг"
    },
    {
        "file": "SATO1.mp3",
        "answer": "Сатана на подработке 1сезон"
    },
    {
        "file": "SHARO.mp3",
        "answer": "Шарлотта"
    },
    {
        "file": "TGO1.mp3",
        "answer": "Токийский гуль 1сезон"
    },
    {
        "file": "TRO.mp3",
        "answer": "Эхо террора"
    },
    {
        "file": "VSO1.mp3",
        "answer": "Сага о Винланде 1сезон 1опенинг"
    },
    {
        "file": "VSO2.mp3",
        "answer": "Сага о Винланде 1сезон 2опенинг"
    },
    {
        "file": "YLAO1.mp3",
        "answer": "Твоя апрельская ложь 1сезон 1опенинг"
    },
    {
        "file": "YLAO2.mp3",
        "answer": "Твоя апрельская ложь 1сезон 2опенинг"
    }
]


